invain/Advanced.py
invain/History.py
invain/Simple.py
invain/Utils.py
invain/__init__.py
invain/__version__.py
invain-0.4.0.dist-info/LICENSE.txt
invain-0.4.0.dist-info/METADATA
invain-0.4.0.dist-info/WHEEL
invain-0.4.0.dist-info/top_level.txt
invain-0.4.0.dist-info/RECORD
