Metadata-Version: 2.1
Name: invain
Version: 0.4.0
Summary: A Python library for getting stock data from Yahoo Finance
Home-page: https://github.com/hailfire113/InVaIN
Author: Alan Arechiga
Author-email: alan@macler.us
License: MIT
Download-URL: https://github.com/hailfire113/InVaIN/archive/0.1.tar.gz
Keywords: invain,stocks,data,finance,yahoo,quotes
Platform: UNKNOWN
Classifier: Development Status :: 3 - Alpha
Classifier: Intended Audience :: Developers
Classifier: Intended Audience :: Financial and Insurance Industry
Classifier: Topic :: Software Development :: Libraries :: Python Modules
Classifier: Topic :: Office/Business :: Financial
Classifier: License :: OSI Approved :: MIT License
Classifier: Programming Language :: Python :: 3
Classifier: Programming Language :: Python :: 3.3
Classifier: Programming Language :: Python :: 3.4
Classifier: Programming Language :: Python :: 3.5
Requires-Dist: requests
